corpus_io/__init__.py
corpus_io/morphemes.py
corpus_io/commons/__init__.py
corpus_io/commons/json_services.py
corpus_io/commons/utils.py
corpus_io/file_io/__init__.py
corpus_io/file_io/morphemes_io.py
corpus_io/nikl/__init__.py
corpus_io/nikl/abc.py
corpus_io/nikl/commons/__init__.py
corpus_io/nikl/commons/mappers.py
corpus_io/nikl/newspapers/__init__.py
corpus_io/nikl/newspapers/services.py
corpus_io/nikl/usecases/__init__.py
corpus_io/nikl/usecases/corpus_merge_usecase.py
corpus_io/nikl/written/__init__.py
corpus_io/nikl/written/services.py
corpus_io-0.0.1.dist-info/LICENSE.txt
corpus_io-0.0.1.dist-info/METADATA
corpus_io-0.0.1.dist-info/WHEEL
corpus_io-0.0.1.dist-info/top_level.txt
corpus_io-0.0.1.dist-info/RECORD
